radio81/__init__.py
radio81/__main__.py
radio81/console.py
radio81/genres.py
radio81/main.py
radio81/parser.py
radio81/player.py
radio81/skeleton.py
radio81-1.4.3.dist-info/LICENSE.txt
radio81-1.4.3.dist-info/WHEEL
radio81-1.4.3.dist-info/METADATA
radio81-1.4.3.dist-info/RECORD
