Metadata-Version: 2.1
Name: radio81
Version: 1.4.3
Summary: Radio81, it's just a radio
Author-email: Cesare Jacopo Corzani <corzani@gmail.com>
Requires-Python: >=3.8
Requires-Dist: inquirerpy~=0.3.4
Requires-Dist: aiohttp~=3.8.5
Requires-Dist: diskcache~=5.6.1
Requires-Dist: appdirs~=1.4.4
Requires-Dist: python-vlc==3.0.18122
